com/__init__.py
com/github/__init__.py
com/github/jelmerk/__init__.py
com/github/jelmerk/spark/__init__.py
com/github/jelmerk/spark/conversion/__init__.py
com/github/jelmerk/spark/knn/__init__.py
com/github/jelmerk/spark/knn/bruteforce/__init__.py
com/github/jelmerk/spark/knn/evaluation/__init__.py
com/github/jelmerk/spark/knn/hnsw/__init__.py
com/github/jelmerk/spark/linalg/__init__.py
pyspark_hnsw/__init__.py
pyspark_hnsw/conversion.py
pyspark_hnsw/evaluation.py
pyspark_hnsw/knn.py
pyspark_hnsw/linalg.py
pyspark_hnsw-1.1.0.dist-info/METADATA
pyspark_hnsw-1.1.0.dist-info/WHEEL
pyspark_hnsw-1.1.0.dist-info/entry_points.txt
pyspark_hnsw-1.1.0.dist-info/top_level.txt
pyspark_hnsw-1.1.0.dist-info/zip-safe
pyspark_hnsw-1.1.0.dist-info/RECORD
